Metadata-Version: 1.0
Name: muldistri
Version: 1.3
Summary: Gaussian and binomial distributions
Home-page: UNKNOWN
Author: AndresGarciaEscalante
Author-email: andres_ge@hotmail.es
License: UNKNOWN
Platform: UNKNOWN
